<?xml version="1.0" encoding="utf-8"?>
<odoo>
    <data>

<!--        <menuitem name="ทะเบียนเช็ค" parent="account.menu_finance_receivables"-->
<!--                  id="menu_ineco_cheque" sequence="30"/>-->

        <!-- ineco.cheque -->
        <record id="view_ineco_cheque_form" model="ir.ui.view">
            <field name="name">ineco.cheque.form</field>
            <field name="model">ineco.cheque</field>
            <field name="arch" type="xml">
                <form string="Cheque" version="7.0" duplicate="0" delete="0">
                    <header>
                        <button name="action_assigned" type="object" states="draft,pending" string="ส่งขึ้นเงิน"/>
                        <button name="action_done" type="object" states="assigned" string="ผ่าน"/>
                        <button name="pending_cheque" type="object" states="reject" string="รอดำเนินการใหม่/พิจารณา"/>
                        <button name="reject_cheque" type="object" states="assigned,pending" string="โดนตีกลับ"/>
                        <button name="cancel_cheque" type="object" states="draft,pending,reject" string="ยกเลิก"/>
                        <button name="action_cancel_draft" type="object" states="cancel" string="กลับไปแก้ไข"/>
                        <button name="action_done_draft" type="object" states="done" string="Set to Draft"/>
                        <field name="state" widget="statusbar"
                               statusbar_visible="cancel,draft,assigned,pending,reject,done"
                               statusbar_colors='{"assigned":"blue"}'/>
                    </header>
                    <sheet>
                        <group>
                            <group>
                                <field name="name" attrs="{'readonly': [('state','not in',('draft'))]}"/>
                                <field name="ref_bank" attrs="{'invisible': [('type', '=', 'out')],'required':[('type', '=', 'in')]}"/>
                                <field name="account_bank_id" domain="[('type','=','bank')]"
                                       attrs="{'readonly': [('state','not in',('draft'))]}"/>
                                <field name="bank" attrs="{'invisible': [('type','=','in')]}" />
                                <field name="partner_id" attrs="{'readonly': [('state','not in',('draft'))]}"/>
                                <field name="amount" attrs="{'readonly': [('state','not in',('draft'))]}"/>
                                <field name="move_line_id" invisible="1" />
                                <field name="customer_payment_id" readonly="1" attrs="{'invisible': [('customer_payment_id', '=', False)]}"/>
                            </group>
                            <group>
                                <field name="cheque_date" attrs="{'readonly': [('state','not in',('draft'))]}"/>
                                <field name="cheque_date_reconcile"
                                       attrs="{'readonly': [('state','not in',('assigned'))]}"/>
                                <field name="type" />
                                <field name="account_receipt_id"
                                       attrs="{'invisible': [('type', '=', 'out')],'required':[('type', '=', 'in')]}"/>
                                <field name="account_pay_id"
                                       attrs="{'invisible': [('type', '=', 'in')],'required':[('type', '=', 'out')]}"/>
                                <field name="move_id" readonly="1"/>
                                <field name="type" required="1" invisible="1"/>
                            </group>
                        </group>
                        <notebook>
                            <page string="Note">
                                <group>
                                    <field name="company_id" groups="base.group_multi_company" required="1"/>
                                </group>
                                <field name="note" colspan="4" attrs="{'readonly': [('state','not in',('draft'))]}"/>
                            </page>
                        </notebook>
                    </sheet>
                    <div class="oe_chatter">
                        <field name="message_follower_ids" groups="base.group_user"/>
                        <field name="activity_ids"/>
                        <field name="message_ids"/>
                    </div>
                </form>
            </field>
        </record>

        <record id="view_ineco_cheque_tree" model="ir.ui.view">
            <field name="name">ineco.cheque.tree</field>
            <field name="model">ineco.cheque</field>
            <field name="arch" type="xml">
                <tree string="Cheque" duplicate="0" delete="0">
                    <field name="type" invisible="0"/>
                    <field name="customer_payment_id" invisible="1" />
                    <field name="customer_deposit_id" invisible="1" />
                    <field name="supplier_payment_id" invisible="1"/>
                    <field name="supplier_deposit_id" invisible="1"/>
                    <field name="name"/>
                    <!--<field name="move_id"/>-->
                    <field name="cheque_date"/>
                    <field name="cheque_date_reconcile"/>
                    <field name="account_bank_id" />
                    <field name="ref_bank"/>
                    <field name="partner_id"/>
                    <field name="amount"/>
                    <field name="company_id"/>
                    <field name="state"/>
                </tree>
            </field>
        </record>

        <record id="view_ineco_cheque_search" model="ir.ui.view">
            <field name="name">ineco.cheque.search</field>
            <field name="model">ineco.cheque</field>
            <field name="arch" type="xml">
                <search string="cheque">
                    <filter icon="terp-document-new" string="Draft" domain="[('state','=','draft')]"
                            name="cheque_draft"/>
                    <filter icon="terp-camera_test" string="Cancel" domain="[('state','=','cancel')]"
                            name="cheque_cancel"/>
                    <filter icon="terp-camera_test" string="Assigned" domain="[('state','=','assigned')]"
                            name="cheque_assigned"/>
                    <filter icon="terp-camera_test" string="Pending" domain="[('state','=','pending')]"
                            name="cheque_pending"/>
                    <filter icon="terp-camera_test" string="Reject" domain="[('state','=','reject')]"
                            name="cheque_reject"/>
                    <filter icon="terp-camera_test" string="Done" domain="[('state','=','done')]" name="cheque_done"/>
                    <field name="name"/>
                    <field name="cheque_date"/>
                    <field name="cheque_date_reconcile"/>
                    <field name="account_bank_id" />
                    <field name="bank"/>
                    <field name="partner_id"/>
                    <!--<field name="voucher_id"/>-->
                    <field name="amount"/>
                </search>
            </field>
        </record>

        <record id="action_ineco_cheque_in_form" model="ir.actions.act_window">
            <field name="name">เช็ครับ</field>
            <field name="res_model">ineco.cheque</field>
            <field name="domain">[('type','=','in')]</field>
            <field name="context">{'default_type': 'in','search_default_cheque_draft': 1, 'type': 'in'}</field>
            <field name="view_mode">tree,form</field>
        </record>

        <menuitem action="action_ineco_cheque_in_form" sequence="121"
                  id="menu_action_ineco_cheque_in_form"
                  parent="account.menu_finance_receivables"/>

        <record id="action_ineco_cheque_out_form" model="ir.actions.act_window">
            <field name="name">เช็คจ่าย</field>
            <field name="res_model">ineco.cheque</field>
            <field name="domain">[('type','=','out')]</field>
            <field name="context">{'default_type': 'out','search_default_cheque_draft': 1, 'type': 'out'}</field>
            <field name="view_mode">tree,form</field>
        </record>

        <menuitem action="action_ineco_cheque_out_form"
                  id="menu_action_ineco_cheque_out_form"
                  name="เช็คจ่าย"
                  parent="account.menu_finance_payables"
                  sequence="4"
        />

    </data>
</odoo>
      